Metadata-Version: 1.0
Name: bayesfit-ap
Version: 0.1.1
Summary: AP's Bayesian fitting and data analysis toolbox.
Home-page: https://github.com/aripekka/bayesfit/
Author: Ari-Pekka Honkanen
Author-email: honkanen.ap@gmail.com
License: UNKNOWN
Platform: UNKNOWN
